odoo/addons/ssi_custom_information_mixin/README.rst
odoo/addons/ssi_custom_information_mixin/__init__.py
odoo/addons/ssi_custom_information_mixin/__manifest__.py
odoo/addons/ssi_custom_information_mixin/menu.xml
odoo/addons/ssi_custom_information_mixin/demo/custom_info_category.xml
odoo/addons/ssi_custom_information_mixin/demo/custom_info_option.xml
odoo/addons/ssi_custom_information_mixin/demo/custom_info_option_set.xml
odoo/addons/ssi_custom_information_mixin/demo/custom_info_property.xml
odoo/addons/ssi_custom_information_mixin/i18n/ssi_custom_information_mixin.pot
odoo/addons/ssi_custom_information_mixin/models/__init__.py
odoo/addons/ssi_custom_information_mixin/models/custom_info_category.py
odoo/addons/ssi_custom_information_mixin/models/custom_info_option.py
odoo/addons/ssi_custom_information_mixin/models/custom_info_option_set.py
odoo/addons/ssi_custom_information_mixin/models/custom_info_property.py
odoo/addons/ssi_custom_information_mixin/models/custom_info_template.py
odoo/addons/ssi_custom_information_mixin/models/custom_info_template_detail.py
odoo/addons/ssi_custom_information_mixin/models/custom_info_value.py
odoo/addons/ssi_custom_information_mixin/models/mixin_custom_info.py
odoo/addons/ssi_custom_information_mixin/security/ir.model.access.csv
odoo/addons/ssi_custom_information_mixin/static/description/icon.png
odoo/addons/ssi_custom_information_mixin/templates/custom_information_templates.xml
odoo/addons/ssi_custom_information_mixin/views/custom_info_category_views.xml
odoo/addons/ssi_custom_information_mixin/views/custom_info_option_set_views.xml
odoo/addons/ssi_custom_information_mixin/views/custom_info_option_views.xml
odoo/addons/ssi_custom_information_mixin/views/custom_info_property_views.xml
odoo/addons/ssi_custom_information_mixin/views/custom_info_template_views.xml
odoo/addons/ssi_custom_information_mixin/views/custom_info_value_views.xml
odoo14_addon_ssi_custom_information_mixin-14.0.3.2.2.dist-info/METADATA
odoo14_addon_ssi_custom_information_mixin-14.0.3.2.2.dist-info/WHEEL
odoo14_addon_ssi_custom_information_mixin-14.0.3.2.2.dist-info/top_level.txt
odoo14_addon_ssi_custom_information_mixin-14.0.3.2.2.dist-info/RECORD
